edgeaudio/__init__.py
edgeaudio/processor.py
edgeaudio/utils.py
edgeaudio/model/__init__.py
edgeaudio/model/lfm2_audio.py
edgeaudio/model/mlp.py
edgeaudio/model/transformer.py
edgeaudio/model/conformer/__init__.py
edgeaudio/model/conformer/encoder.py
edgeaudio/model/conformer/mha.py
edgeaudio/model/conformer/modules.py
edgeaudio/model/conformer/processor.py
edgeaudio/model/conformer/subsampling.py
edgeaudio/model/conformer/utils.py
edgeaudio/moshi/__init__.py
edgeaudio/moshi/client.py
edgeaudio/moshi/client_gradio.py
edgeaudio/moshi/client_utils.py
edgeaudio/moshi/run_inference.py
edgeaudio/moshi/run_tts.py
edgeaudio/moshi/server.py
edgeaudio/moshi/conditioners/__init__.py
edgeaudio/moshi/conditioners/base.py
edgeaudio/moshi/conditioners/tensors.py
edgeaudio/moshi/conditioners/text.py
edgeaudio/moshi/models/__init__.py
edgeaudio/moshi/models/compression.py
edgeaudio/moshi/models/lm.py
edgeaudio/moshi/models/lm_utils.py
edgeaudio/moshi/models/loaders.py
edgeaudio/moshi/models/tts.py
edgeaudio/moshi/modules/__init__.py
edgeaudio/moshi/modules/conv.py
edgeaudio/moshi/modules/conv_test.py
edgeaudio/moshi/modules/gating.py
edgeaudio/moshi/modules/lora.py
edgeaudio/moshi/modules/resample.py
edgeaudio/moshi/modules/rope.py
edgeaudio/moshi/modules/seanet.py
edgeaudio/moshi/modules/seanet_test.py
edgeaudio/moshi/modules/streaming.py
edgeaudio/moshi/modules/transformer.py
edgeaudio/moshi/quantization/__init__.py
edgeaudio/moshi/quantization/base.py
edgeaudio/moshi/quantization/core_vq.py
edgeaudio/moshi/quantization/vq.py
edgeaudio/moshi/utils/__init__.py
edgeaudio/moshi/utils/autocast.py
edgeaudio/moshi/utils/compile.py
edgeaudio/moshi/utils/quantize.py
edgeaudio/moshi/utils/sampling.py
edgeaudio/moshi/utils/utils.py
edgeaudio-0.0.2.dist-info/LICENSE
edgeaudio-0.0.2.dist-info/WHEEL
edgeaudio-0.0.2.dist-info/METADATA
edgeaudio-0.0.2.dist-info/RECORD
