Metadata-Version: 2.1
Name: edgeaudio
Version: 0.0.2
Summary: GGUF connector(s) with GUI
Author-email: calcuis <info@calcu.io>
Classifier: License :: OSI Approved :: MIT License
